fhem/__init__.py
fhem-0.7.0.dist-info/METADATA
fhem-0.7.0.dist-info/WHEEL
fhem-0.7.0.dist-info/top_level.txt
fhem-0.7.0.dist-info/RECORD
