Metadata-Version: 2.1
Name: fhem
Version: 0.7.0
Summary: Python API for FHEM home automation server
Home-page: http://github.com/domschl/python-fhem
Author: Dominik Schloesser
Author-email: dsc@dosc.net
Project-URL: Bug Tracker, https://github.com/domschl/python-fhem/issues
Classifier: Programming Language :: Python :: 3
Classifier: Development Status :: 5 - Production/Stable
Classifier: License :: OSI Approved :: MIT License
Classifier: Operating System :: OS Independent
Requires-Python: >=3.6
